mortal_sql/__init__.py
mortal_sql/execute_main.cp37-win_amd64.pyd
mortal_sql/orm_main.cp37-win_amd64.pyd
mortal_sql/domian/__init__.py
mortal_sql/domian/hive.cp37-win_amd64.pyd
mortal_sql/domian/impala.cp37-win_amd64.pyd
mortal_sql/domian/mysql.cp37-win_amd64.pyd
mortal_sql/domian/oracle.cp37-win_amd64.pyd
mortal_sql/domian/postgresql.cp37-win_amd64.pyd
mortal_sql/domian/sqlite.cp37-win_amd64.pyd
mortal_sql/domian/sqlserver.cp37-win_amd64.pyd
mortal_sql/domian/starrocks.cp37-win_amd64.pyd
mortal_sql/utils/__init__.py
mortal_sql/utils/get_domain_mapping.cp37-win_amd64.pyd
mortal_sql/utils/universal_method.cp37-win_amd64.pyd
mortal_sql-4.4.0.dist-info/METADATA
mortal_sql-4.4.0.dist-info/WHEEL
mortal_sql-4.4.0.dist-info/top_level.txt
mortal_sql-4.4.0.dist-info/RECORD
