Metadata-Version: 2.1
Name: mortal-sql
Version: 4.4.0
Summary: mortal工具集::mortal_sql
Home-page: https://www.example.com
Author: Mortal
Author-email: mortal9098@163.com
License: MIT
Classifier: Development Status :: 4 - Beta
Classifier: Programming Language :: Python :: 3
Classifier: Programming Language :: Python :: 3.7
Classifier: Operating System :: Microsoft :: Windows
Classifier: Intended Audience :: Developers
Requires-Python: >=3.7
Requires-Dist: mortal-crypt
Requires-Dist: ms9
Requires-Dist: mortal-var
Requires-Dist: mortal-log
Requires-Dist: mortal-threads
Requires-Dist: mortal-ssh
Requires-Dist: numpy
Requires-Dist: pandas
Requires-Dist: SQLAlchemy
Requires-Dist: PyMySQL
Requires-Dist: GeoAlchemy2
Requires-Dist: sqlacodegen
